speaky/__init__.py
speaky/_suppress_warnings.py
speaky/_version.py
speaky/cli.py
speaky/core.py
speaky/glitch_detection.py
speaky/transcription.py
speaky/tts.py
speaky/voices/__init__.py
speaky/voices/attenborough.mp3
speaky/voices/her.mp3
speaky/voices/kamala.mp3
speaky/voices/siri.mp3
speaky/voices/trump.mp3
speaky/voices/vader.mp3
speaky-0.1.1.dist-info/METADATA
speaky-0.1.1.dist-info/WHEEL
speaky-0.1.1.dist-info/entry_points.txt
speaky-0.1.1.dist-info/top_level.txt
speaky-0.1.1.dist-info/RECORD
