Metadata-Version: 2.4
Name: speaky
Version: 0.1.1
Summary: Text to speech with voice cloning
Author: Bryce Drennan
License-Expression: MIT
Project-URL: Documentation, https://github.com/brycedrennan/speaky
Project-URL: Source, https://github.com/brycedrennan/speaky
Requires-Python: >=3.12.8
Requires-Dist: chatterbox-tts>=0.1.0
Requires-Dist: torch>=2.2
Requires-Dist: torchaudio>=2.2
Requires-Dist: typer>=0.12
Requires-Dist: nltk>=3.8
Requires-Dist: pathspec
Requires-Dist: numpy>=1.26
Requires-Dist: scipy>=1.11
Requires-Dist: transformers>=4.36
Requires-Dist: accelerate>=0.24
